trame/modules/gofish.py
trame/widgets/gofish.py
trame_gofish/__init__.py
trame_gofish/module/__init__.py
trame_gofish/module/serve/trame_gofish.umd.js
trame_gofish/widgets/__init__.py
trame_gofish/widgets/gofish.py
trame_gofish-1.0.0.dist-info/METADATA
trame_gofish-1.0.0.dist-info/WHEEL
trame_gofish-1.0.0.dist-info/licenses/LICENSE
trame_gofish-1.0.0.dist-info/RECORD
